[{"timestamp":"2025-05-31T01:22:03.041Z","count":0,"uniques":0},{"timestamp":"2025-06-01T01:47:26.320Z","count":0,"uniques":0},{"timestamp":"2025-06-02T01:27:26.403Z","count":0,"uniques":0},{"timestamp":"2025-06-03T01:25:19.773Z","count":0,"uniques":0},{"timestamp":"2025-06-04T01:25:20.184Z","count":0,"uniques":0},{"timestamp":"2025-06-05T01:24:11.227Z","count":0,"uniques":0},{"timestamp":"2025-06-06T01:24:01.209Z","count":0,"uniques":0},{"timestamp":"2025-06-07T01:23:40.696Z","count":0,"uniques":0}]
