[{"timestamp":"2022-05-01T17:00:32.549Z","count":0,"uniques":0},{"timestamp":"2022-06-01T17:00:32.549Z","count":0,"uniques":0},{"timestamp":"2022-07-01T17:00:32.549Z","count":0,"uniques":0},{"timestamp":"2022-08-01T17:00:32.549Z","count":0,"uniques":0},{"timestamp":"2022-09-01T17:00:32.549Z","count":0,"uniques":0},{"timestamp":"2022-10-01T16:34:48.848Z","count":3,"uniques":1},{"timestamp":"2022-11-01T17:32:14.949Z","count":11,"uniques":2},{"timestamp":"2022-12-01T12:22:26.364Z","count":18,"uniques":3},{"timestamp":"2023-01-01T01:05:37.590Z","count":5,"uniques":3},{"timestamp":"2023-02-01T12:28:05.314Z","count":57,"uniques":3},{"timestamp":"2023-03-01T01:14:32.312Z","count":2,"uniques":2},{"timestamp":"2023-04-01T01:05:19.163Z","count":0,"uniques":0},{"timestamp":"2023-05-01T13:00:10.527Z","count":76,"uniques":5}]
