[{"timestamp":"2024-08-12T01:06:37.950Z","count":0,"uniques":0},{"timestamp":"2024-08-13T01:06:03.022Z","count":0,"uniques":0},{"timestamp":"2024-08-14T01:05:05.807Z","count":0,"uniques":0},{"timestamp":"2024-08-15T01:02:08.532Z","count":0,"uniques":0},{"timestamp":"2024-08-16T01:04:27.920Z","count":0,"uniques":0},{"timestamp":"2024-08-17T01:02:40.627Z","count":0,"uniques":0},{"timestamp":"2024-08-18T01:09:04.826Z","count":0,"uniques":0},{"timestamp":"2024-08-19T01:05:45.568Z","count":0,"uniques":0}]
