[{"timestamp":"2024-12-17T01:18:46.545Z","count":0,"uniques":0},{"timestamp":"2024-12-18T01:15:41.225Z","count":0,"uniques":0},{"timestamp":"2024-12-19T00:00:00.000Z","count":7,"uniques":1},{"timestamp":"2024-12-20T00:00:00.000Z","count":11,"uniques":1},{"timestamp":"2024-12-21T01:11:26.857Z","count":0,"uniques":0},{"timestamp":"2024-12-22T01:18:14.373Z","count":0,"uniques":0},{"timestamp":"2024-12-23T01:14:07.083Z","count":0,"uniques":0},{"timestamp":"2024-12-24T01:12:33.755Z","count":0,"uniques":0}]
