[{"timestamp":"2025-03-25T01:18:18.303Z","count":0,"uniques":0},{"timestamp":"2025-03-26T00:00:00.000Z","count":1,"uniques":1},{"timestamp":"2025-03-27T01:17:17.879Z","count":0,"uniques":0},{"timestamp":"2025-03-28T00:00:00.000Z","count":2,"uniques":1},{"timestamp":"2025-03-29T01:16:45.162Z","count":0,"uniques":0},{"timestamp":"2025-03-30T01:23:55.031Z","count":0,"uniques":0},{"timestamp":"2025-03-31T01:21:47.898Z","count":0,"uniques":0},{"timestamp":"2025-04-01T01:26:55.596Z","count":0,"uniques":0}]
