[{"timestamp":"2025-10-14T01:17:40.425Z","count":0,"uniques":0},{"timestamp":"2025-10-15T01:19:59.079Z","count":0,"uniques":0},{"timestamp":"2025-10-16T01:19:08.532Z","count":0,"uniques":0},{"timestamp":"2025-10-17T01:19:09.763Z","count":0,"uniques":0},{"timestamp":"2025-10-18T01:15:12.003Z","count":0,"uniques":0},{"timestamp":"2025-10-19T01:27:50.171Z","count":0,"uniques":0},{"timestamp":"2025-10-20T00:00:00.000Z","count":6,"uniques":6},{"timestamp":"2025-10-21T01:21:21.701Z","count":0,"uniques":0}]
